mcp_long_context_reader/__init__.py
mcp_long_context_reader/cache_manager.py
mcp_long_context_reader/context.py
mcp_long_context_reader/inspector.py
mcp_long_context_reader/server.py
mcp_long_context_reader/utils.py
mcp_long_context_reader/strategies/__init__.py
mcp_long_context_reader/strategies/base.py
mcp_long_context_reader/strategies/map_reduce_summary.py
mcp_long_context_reader/strategies/rag_retrieval.py
mcp_long_context_reader/strategies/regex_search.py
mcp_long_context_reader/strategies/sequential_notes.py
mcp_long_context_reader-0.9.0.dist-info/METADATA
mcp_long_context_reader-0.9.0.dist-info/WHEEL
mcp_long_context_reader-0.9.0.dist-info/entry_points.txt
mcp_long_context_reader-0.9.0.dist-info/licenses/LICENSE
mcp_long_context_reader-0.9.0.dist-info/RECORD
