Metadata-Version: 2.4
Name: mcp-long-context-reader
Version: 0.9.0
Summary: A tool to help agents read and query long documents.
Project-URL: Homepage, https://github.com/yuplin2333/mcp-long-context-reader
Project-URL: Repository, https://github.com/yuplin2333/mcp-long-context-reader
Project-URL: Issues, https://github.com/yuplin2333/mcp-long-context-reader/issues
Project-URL: Documentation, https://github.com/yuplin2333/mcp-long-context-reader#readme
Author-email: Yuping Lin <linyupin@msu.edu>, Zitao Li <zitao.l@alibaba-inc.com>
Maintainer-email: Yuping Lin <linyupin@msu.edu>, Zitao Li <zitao.l@alibaba-inc.com>
License: MIT
License-File: LICENSE
Keywords: document,llm,long-context,mcp,rag,reader,summarization
Classifier: Development Status :: 4 - Beta
Classifier: Intended Audience :: Developers
Classifier: License :: OSI Approved :: MIT License
Classifier: Programming Language :: Python :: 3
Classifier: Programming Language :: Python :: 3.10
Classifier: Programming Language :: Python :: 3.11
Classifier: Programming Language :: Python :: 3.12
Classifier: Topic :: Scientific/Engineering :: Artificial Intelligence
Classifier: Topic :: Software Development :: Libraries :: Python Modules
Classifier: Topic :: Text Processing :: General
Requires-Python: >=3.10
Requires-Dist: dashscope>=1.23.5
Requires-Dist: faiss-cpu>=1.11.0
Requires-Dist: fastmcp>=2.8.1
Requires-Dist: langchain-community>=0.3.25
Requires-Dist: langchain-openai>=0.3.24
Requires-Dist: langchain>=0.3.25
Requires-Dist: tiktoken>=0.9.0
Requires-Dist: transformers>=4.52.4
